tk_helper/TKHelper.py
tk_helper/__init__.py
tk_helper/__version__.py
tk_helper-1.0.1.dist-info/LICENSE
tk_helper-1.0.1.dist-info/METADATA
tk_helper-1.0.1.dist-info/WHEEL
tk_helper-1.0.1.dist-info/top_level.txt
tk_helper-1.0.1.dist-info/RECORD
