Metadata-Version: 2.1
Name: tk-helper
Version: 1.0.1
Summary: Helper routines for TTK widgets
Home-page: https://github.com/corb555/tk_helper
Author: Mike Herbert
Author-email: corb@aol.com
License: MIT
Platform: UNKNOWN
Classifier: Programming Language :: Python :: 3.6
Classifier: License :: OSI Approved :: BSD License
Classifier: Operating System :: OS Independent
Classifier: Development Status :: 4 - Beta
Classifier: Intended Audience :: Developers
Classifier: Natural Language :: English
Classifier: Topic :: Software Development :: User Interfaces
